run.py
setup.py
deadcheck/ErrorCodes.py
deadcheck/ErrorHandler.py
deadcheck/URLLinks.py
deadcheck/__init__.py
deadcheck/deadcheck.py
deadcheck.egg-info/PKG-INFO
deadcheck.egg-info/SOURCES.txt
deadcheck.egg-info/dependency_links.txt
deadcheck.egg-info/requires.txt
deadcheck.egg-info/top_level.txt
deadcheck/report/Report.py
deadcheck/report/__init__.py
deadcheck/report/Templates/Report.css
deadcheck/report/Templates/head.template
deadcheck/report/Templates/table.template
deadcheck/report/Templates/tail.template
t/__init__.py
t/test.py
t/test_suite.py